periodicencryption/__init__.py
periodicencryption/element.py
periodicencryption/encryption.py
periodicencryption/vigenerecipher.py
periodicencryption-1.1.4.dist-info/LICENSE.txt
periodicencryption-1.1.4.dist-info/METADATA
periodicencryption-1.1.4.dist-info/WHEEL
periodicencryption-1.1.4.dist-info/top_level.txt
periodicencryption-1.1.4.dist-info/RECORD
