Metadata-Version: 2.1
Name: periodicencryption
Version: 1.1.4
Summary: Allows you to encrypt and decrypt messages by the mean of Vigenere Cipher and Periodic Table of Elements
Home-page: https://github.com/NilsMT/periodic-encryption
Author: NilsMT
Author-email: nilsmoreauthomas@gmail.com
License: MIT
Keywords: CRYPTOGRAPHY,SECURITY,PERIODIC TABLE,CHEMICAL,WEIRD
Classifier: Development Status :: 5 - Production/Stable
Classifier: Intended Audience :: Developers
Classifier: Topic :: Security :: Cryptography
Classifier: License :: OSI Approved :: MIT License
Classifier: Programming Language :: Python :: 3.9
Classifier: Programming Language :: Python :: 3.10
Classifier: Programming Language :: Python :: 3.11
License-File: LICENSE.txt
Requires-Dist: periodictable
Requires-Dist: numpy
Requires-Dist: pandas
